{"experimentName": "BBQ-2", "lead": {"deviceName": "Postman", "temporaryTracingKeys": [{"key": "gHar/BAhqOm9cBvrZM37Qg==", "intervalCount": 144, "intervalNumber": 2655216}]}, "requestedConfigurations": [{"attenuationDurationThresholds": [55, 63, 90]}], "participants": [{"deviceName": "7018", "temporaryTracingKeys": [{"key": "vFtswO7YMkRtunVvG6eIEQ==", "intervalCount": 144, "intervalNumber": 2669328}], "results": [{"counterparts": [{"deviceName": "7018", "exposureWindows": []}, {"deviceName": "7019", "exposureWindows": [{"date": "2020-10-02T00:00:00Z", "scanInstances": [{"typicalAttenuationDb": 50, "minAttenuationDb": 45, "secondsSinceLastScan": 180}, {"typicalAttenuationDb": 56, "minAttenuationDb": 53, "secondsSinceLastScan": 300}, {"typicalAttenuationDb": 75, "minAttenuationDb": 69, "secondsSinceLastScan": 240}, {"typicalAttenuationDb": 67, "minAttenuationDb": 60, "secondsSinceLastScan": 240}, {"typicalAttenuationDb": 69, "minAttenuationDb": 62, "secondsSinceLastScan": 180}], "reportType": 0}, {"date": "2020-10-02T00:00:00Z", "scanInstances": [{"typicalAttenuationDb": 56, "minAttenuationDb": 56, "secondsSinceLastScan": 180}], "reportType": 0}]}, {"deviceName": "7016", "exposureWindows": [{"date": "2020-10-02T00:00:00Z", "scanInstances": [{"typicalAttenuationDb": 22, "minAttenuationDb": 19, "secondsSinceLastScan": 180}, {"typicalAttenuationDb": 75, "minAttenuationDb": 72, "secondsSinceLastScan": 300}, {"typicalAttenuationDb": 85, "minAttenuationDb": 79, "secondsSinceLastScan": 240}, {"typicalAttenuationDb": 84, "minAttenuationDb": 76, "secondsSinceLastScan": 240}, {"typicalAttenuationDb": 73, "minAttenuationDb": 67, "secondsSinceLastScan": 180}], "reportType": 0}]}, {"deviceName": "7004", "exposureWindows": [{"date": "2020-10-02T00:00:00Z", "scanInstances": [{"typicalAttenuationDb": 44, "minAttenuationDb": 44, "secondsSinceLastScan": 300}], "reportType": 0}, {"date": "2020-10-02T00:00:00Z", "scanInstances": [{"typicalAttenuationDb": 48, "minAttenuationDb": 48, "secondsSinceLastScan": 60}], "reportType": 0}, {"date": "2020-10-02T00:00:00Z", "scanInstances": [{"typicalAttenuationDb": 60, "minAttenuationDb": 51, "secondsSinceLastScan": 300}, {"typicalAttenuationDb": 65, "minAttenuationDb": 62, "secondsSinceLastScan": 180}, {"typicalAttenuationDb": 66, "minAttenuationDb": 65, "secondsSinceLastScan": 240}, {"typicalAttenuationDb": 48, "minAttenuationDb": 39, "secondsSinceLastScan": 180}], "reportType": 0}, {"date": "2020-10-02T00:00:00Z", "scanInstances": [{"typicalAttenuationDb": 53, "minAttenuationDb": 53, "secondsSinceLastScan": 180}], "reportType": 0}]}, {"deviceName": "7008", "exposureWindows": [{"date": "2020-10-02T00:00:00Z", "scanInstances": [{"typicalAttenuationDb": 71, "minAttenuationDb": 70, "secondsSinceLastScan": 180}], "reportType": 0}, {"date": "2020-10-02T00:00:00Z", "scanInstances": [{"typicalAttenuationDb": 43, "minAttenuationDb": 39, "secondsSinceLastScan": 180}, {"typicalAttenuationDb": 69, "minAttenuationDb": 69, "secondsSinceLastScan": 300}, {"typicalAttenuationDb": 82, "minAttenuationDb": 76, "secondsSinceLastScan": 300}, {"typicalAttenuationDb": 89, "minAttenuationDb": 78, "secondsSinceLastScan": 180}, {"typicalAttenuationDb": 88, "minAttenuationDb": 83, "secondsSinceLastScan": 240}, {"typicalAttenuationDb": 82, "minAttenuationDb": 77, "secondsSinceLastScan": 180}], "reportType": 0}]}, {"deviceName": "7030", "exposureWindows": [{"date": "2020-10-02T00:00:00Z", "scanInstances": [{"typicalAttenuationDb": 64, "minAttenuationDb": 61, "secondsSinceLastScan": 300}, {"typicalAttenuationDb": 73, "minAttenuationDb": 73, "secondsSinceLastScan": 240}, {"typicalAttenuationDb": 71, "minAttenuationDb": 68, "secondsSinceLastScan": 180}, {"typicalAttenuationDb": 68, "minAttenuationDb": 66, "secondsSinceLastScan": 180}], "reportType": 0}, {"date": "2020-10-02T00:00:00Z", "scanInstances": [{"typicalAttenuationDb": 63, "minAttenuationDb": 63, "secondsSinceLastScan": 180}], "reportType": 0}, {"date": "2020-10-02T00:00:00Z", "scanInstances": [{"typicalAttenuationDb": 68, "minAttenuationDb": 68, "secondsSinceLastScan": 180}], "reportType": 0}]}, {"deviceName": "7013", "exposureWindows": [{"date": "2020-10-02T00:00:00Z", "scanInstances": [{"typicalAttenuationDb": 72, "minAttenuationDb": 72, "secondsSinceLastScan": 300}, {"typicalAttenuationDb": 74, "minAttenuationDb": 74, "secondsSinceLastScan": 240}, {"typicalAttenuationDb": 71, "minAttenuationDb": 71, "secondsSinceLastScan": 60}], "reportType": 0}]}, {"deviceName": "7011", "exposureWindows": [{"date": "2020-10-02T00:00:00Z", "scanInstances": [{"typicalAttenuationDb": 66, "minAttenuationDb": 61, "secondsSinceLastScan": 180}, {"typicalAttenuationDb": 61, "minAttenuationDb": 54, "secondsSinceLastScan": 180}], "reportType": 0}, {"date": "2020-10-02T00:00:00Z", "scanInstances": [{"typicalAttenuationDb": 50, "minAttenuationDb": 47, "secondsSinceLastScan": 300}, {"typicalAttenuationDb": 62, "minAttenuationDb": 58, "secondsSinceLastScan": 240}], "reportType": 0}]}], "timestamp": "2020-10-02T16:32:15Z"}]}, {"deviceName": "7019", "temporaryTracingKeys": [{"key": "7GMWx0CNJuadULfCc7Ob3A==", "intervalCount": 144, "intervalNumber": 2669328}], "results": [{"counterparts": [{"deviceName": "7018", "exposureWindows": [{"date": "2020-10-02T00:00:00Z", "scanInstances": [{"typicalAttenuationDb": 69, "minAttenuationDb": 69, "secondsSinceLastScan": 180}], "reportType": 0}, {"date": "2020-10-02T00:00:00Z", "scanInstances": [{"typicalAttenuationDb": 44, "minAttenuationDb": 38, "secondsSinceLastScan": 240}, {"typicalAttenuationDb": 65, "minAttenuationDb": 64, "secondsSinceLastScan": 300}, {"typicalAttenuationDb": 59, "minAttenuationDb": 55, "secondsSinceLastScan": 180}, {"typicalAttenuationDb": 71, "minAttenuationDb": 66, "secondsSinceLastScan": 240}, {"typicalAttenuationDb": 69, "minAttenuationDb": 61, "secondsSinceLastScan": 180}, {"typicalAttenuationDb": 72, "minAttenuationDb": 58, "secondsSinceLastScan": 240}, {"typicalAttenuationDb": 62, "minAttenuationDb": 62, "secondsSinceLastScan": 180}], "reportType": 0}]}, {"deviceName": "7019", "exposureWindows": []}, {"deviceName": "7016", "exposureWindows": [{"date": "2020-10-02T00:00:00Z", "scanInstances": [{"typicalAttenuationDb": 45, "minAttenuationDb": 42, "secondsSinceLastScan": 240}, {"typicalAttenuationDb": 72, "minAttenuationDb": 70, "secondsSinceLastScan": 180}, {"typicalAttenuationDb": 75, "minAttenuationDb": 70, "secondsSinceLastScan": 240}, {"typicalAttenuationDb": 79, "minAttenuationDb": 77, "secondsSinceLastScan": 180}, {"typicalAttenuationDb": 76, "minAttenuationDb": 73, "secondsSinceLastScan": 240}, {"typicalAttenuationDb": 77, "minAttenuationDb": 65, "secondsSinceLastScan": 180}], "reportType": 0}]}, {"deviceName": "7004", "exposureWindows": [{"date": "2020-10-02T00:00:00Z", "scanInstances": [{"typicalAttenuationDb": 61, "minAttenuationDb": 55, "secondsSinceLastScan": 240}, {"typicalAttenuationDb": 60, "minAttenuationDb": 49, "secondsSinceLastScan": 180}, {"typicalAttenuationDb": 56, "minAttenuationDb": 43, "secondsSinceLastScan": 240}], "reportType": 0}, {"date": "2020-10-02T00:00:00Z", "scanInstances": [{"typicalAttenuationDb": 58, "minAttenuationDb": 48, "secondsSinceLastScan": 180}], "reportType": 0}]}, {"deviceName": "7008", "exposureWindows": [{"date": "2020-10-02T00:00:00Z", "scanInstances": [{"typicalAttenuationDb": 84, "minAttenuationDb": 72, "secondsSinceLastScan": 240}, {"typicalAttenuationDb": 76, "minAttenuationDb": 76, "secondsSinceLastScan": 180}], "reportType": 0}, {"date": "2020-10-02T00:00:00Z", "scanInstances": [{"typicalAttenuationDb": 30, "minAttenuationDb": 28, "secondsSinceLastScan": 240}, {"typicalAttenuationDb": 32, "minAttenuationDb": 31, "secondsSinceLastScan": 240}, {"typicalAttenuationDb": 87, "minAttenuationDb": 85, "secondsSinceLastScan": 180}, {"typicalAttenuationDb": 85, "minAttenuationDb": 79, "secondsSinceLastScan": 240}, {"typicalAttenuationDb": 84, "minAttenuationDb": 79, "secondsSinceLastScan": 180}], "reportType": 0}]}, {"deviceName": "7030", "exposureWindows": [{"date": "2020-10-02T00:00:00Z", "scanInstances": [{"typicalAttenuationDb": 70, "minAttenuationDb": 67, "secondsSinceLastScan": 180}, {"typicalAttenuationDb": 59, "minAttenuationDb": 48, "secondsSinceLastScan": 240}, {"typicalAttenuationDb": 65, "minAttenuationDb": 65, "secondsSinceLastScan": 180}, {"typicalAttenuationDb": 71, "minAttenuationDb": 71, "secondsSinceLastScan": 240}], "reportType": 0}, {"date": "2020-10-02T00:00:00Z", "scanInstances": [{"typicalAttenuationDb": 63, "minAttenuationDb": 63, "secondsSinceLastScan": 180}], "reportType": 0}]}, {"deviceName": "7013", "exposureWindows": [{"date": "2020-10-02T00:00:00Z", "scanInstances": [{"typicalAttenuationDb": 60, "minAttenuationDb": 60, "secondsSinceLastScan": 240}, {"typicalAttenuationDb": 77, "minAttenuationDb": 77, "secondsSinceLastScan": 240}, {"typicalAttenuationDb": 59, "minAttenuationDb": 59, "secondsSinceLastScan": 180}], "reportType": 0}]}, {"deviceName": "7011", "exposureWindows": [{"date": "2020-10-02T00:00:00Z", "scanInstances": [{"typicalAttenuationDb": 54, "minAttenuationDb": 48, "secondsSinceLastScan": 180}, {"typicalAttenuationDb": 60, "minAttenuationDb": 55, "secondsSinceLastScan": 240}, {"typicalAttenuationDb": 58, "minAttenuationDb": 53, "secondsSinceLastScan": 180}], "reportType": 0}, {"date": "2020-10-02T00:00:00Z", "scanInstances": [{"typicalAttenuationDb": 49, "minAttenuationDb": 49, "secondsSinceLastScan": 180}], "reportType": 0}, {"date": "2020-10-02T00:00:00Z", "scanInstances": [{"typicalAttenuationDb": 57, "minAttenuationDb": 48, "secondsSinceLastScan": 240}], "reportType": 0}]}], "timestamp": "2020-10-02T16:32:32Z"}]}, {"deviceName": "7016", "temporaryTracingKeys": [{"key": "uBBUke9AsaPRdDZJ+lE2vA==", "intervalCount": 144, "intervalNumber": 2669328}], "results": [{"counterparts": [{"deviceName": "7018", "exposureWindows": [{"date": "2020-10-02T00:00:00Z", "scanInstances": [{"typicalAttenuationDb": 77, "minAttenuationDb": 77, "secondsSinceLastScan": 180}], "reportType": 0}, {"date": "2020-10-02T00:00:00Z", "scanInstances": [{"typicalAttenuationDb": 51, "minAttenuationDb": 47, "secondsSinceLastScan": 180}, {"typicalAttenuationDb": 78, "minAttenuationDb": 78, "secondsSinceLastScan": 300}, {"typicalAttenuationDb": 78, "minAttenuationDb": 71, "secondsSinceLastScan": 180}, {"typicalAttenuationDb": 81, "minAttenuationDb": 74, "secondsSinceLastScan": 240}, {"typicalAttenuationDb": 86, "minAttenuationDb": 82, "secondsSinceLastScan": 180}, {"typicalAttenuationDb": 87, "minAttenuationDb": 82, "secondsSinceLastScan": 120}, {"typicalAttenuationDb": 77, "minAttenuationDb": 73, "secondsSinceLastScan": 180}], "reportType": 0}]}, {"deviceName": "7019", "exposureWindows": [{"date": "2020-10-02T00:00:00Z", "scanInstances": [{"typicalAttenuationDb": 73, "minAttenuationDb": 72, "secondsSinceLastScan": 180}], "reportType": 0}, {"date": "2020-10-02T00:00:00Z", "scanInstances": [{"typicalAttenuationDb": 24, "minAttenuationDb": 22, "secondsSinceLastScan": 180}, {"typicalAttenuationDb": 76, "minAttenuationDb": 76, "secondsSinceLastScan": 300}, {"typicalAttenuationDb": 69, "minAttenuationDb": 67, "secondsSinceLastScan": 180}, {"typicalAttenuationDb": 68, "minAttenuationDb": 63, "secondsSinceLastScan": 240}, {"typicalAttenuationDb": 69, "minAttenuationDb": 65, "secondsSinceLastScan": 180}, {"typicalAttenuationDb": 71, "minAttenuationDb": 62, "secondsSinceLastScan": 120}, {"typicalAttenuationDb": 75, "minAttenuationDb": 71, "secondsSinceLastScan": 180}], "reportType": 0}]}, {"deviceName": "7016", "exposureWindows": []}, {"deviceName": "7004", "exposureWindows": [{"date": "2020-10-02T00:00:00Z", "scanInstances": [{"typicalAttenuationDb": 57, "minAttenuationDb": 54, "secondsSinceLastScan": 240}, {"typicalAttenuationDb": 67, "minAttenuationDb": 65, "secondsSinceLastScan": 240}, {"typicalAttenuationDb": 65, "minAttenuationDb": 62, "secondsSinceLastScan": 180}], "reportType": 0}, {"date": "2020-10-02T00:00:00Z", "scanInstances": [{"typicalAttenuationDb": 64, "minAttenuationDb": 64, "secondsSinceLastScan": 300}], "reportType": 0}]}, {"deviceName": "7008", "exposureWindows": [{"date": "2020-10-02T00:00:00Z", "scanInstances": [{"typicalAttenuationDb": 62, "minAttenuationDb": 59, "secondsSinceLastScan": 180}], "reportType": 0}, {"date": "2020-10-02T00:00:00Z", "scanInstances": [{"typicalAttenuationDb": 28, "minAttenuationDb": 27, "secondsSinceLastScan": 180}, {"typicalAttenuationDb": 59, "minAttenuationDb": 57, "secondsSinceLastScan": 300}, {"typicalAttenuationDb": 65, "minAttenuationDb": 59, "secondsSinceLastScan": 180}, {"typicalAttenuationDb": 59, "minAttenuationDb": 55, "secondsSinceLastScan": 240}, {"typicalAttenuationDb": 59, "minAttenuationDb": 55, "secondsSinceLastScan": 180}, {"typicalAttenuationDb": 60, "minAttenuationDb": 56, "secondsSinceLastScan": 120}, {"typicalAttenuationDb": 56, "minAttenuationDb": 54, "secondsSinceLastScan": 180}], "reportType": 0}]}, {"deviceName": "7030", "exposureWindows": [{"date": "2020-10-02T00:00:00Z", "scanInstances": [{"typicalAttenuationDb": 55, "minAttenuationDb": 55, "secondsSinceLastScan": 300}, {"typicalAttenuationDb": 64, "minAttenuationDb": 59, "secondsSinceLastScan": 180}, {"typicalAttenuationDb": 63, "minAttenuationDb": 59, "secondsSinceLastScan": 240}, {"typicalAttenuationDb": 60, "minAttenuationDb": 58, "secondsSinceLastScan": 180}, {"typicalAttenuationDb": 61, "minAttenuationDb": 57, "secondsSinceLastScan": 120}, {"typicalAttenuationDb": 59, "minAttenuationDb": 57, "secondsSinceLastScan": 180}], "reportType": 0}]}, {"deviceName": "7013", "exposureWindows": [{"date": "2020-10-02T00:00:00Z", "scanInstances": [{"typicalAttenuationDb": 57, "minAttenuationDb": 55, "secondsSinceLastScan": 300}, {"typicalAttenuationDb": 72, "minAttenuationDb": 71, "secondsSinceLastScan": 180}, {"typicalAttenuationDb": 72, "minAttenuationDb": 71, "secondsSinceLastScan": 240}, {"typicalAttenuationDb": 72, "minAttenuationDb": 71, "secondsSinceLastScan": 180}, {"typicalAttenuationDb": 71, "minAttenuationDb": 70, "secondsSinceLastScan": 120}, {"typicalAttenuationDb": 69, "minAttenuationDb": 67, "secondsSinceLastScan": 180}], "reportType": 0}]}, {"deviceName": "7011", "exposureWindows": [{"date": "2020-10-02T00:00:00Z", "scanInstances": [{"typicalAttenuationDb": 71, "minAttenuationDb": 68, "secondsSinceLastScan": 180}, {"typicalAttenuationDb": 71, "minAttenuationDb": 69, "secondsSinceLastScan": 180}], "reportType": 0}, {"date": "2020-10-02T00:00:00Z", "scanInstances": [{"typicalAttenuationDb": 69, "minAttenuationDb": 69, "secondsSinceLastScan": 300}, {"typicalAttenuationDb": 67, "minAttenuationDb": 61, "secondsSinceLastScan": 0}, {"typicalAttenuationDb": 64, "minAttenuationDb": 59, "secondsSinceLastScan": 180}, {"typicalAttenuationDb": 64, "minAttenuationDb": 63, "secondsSinceLastScan": 180}], "reportType": 0}]}], "timestamp": "2020-10-02T16:30:15Z"}]}, {"deviceName": "7004", "googlePlayServicesVersion": "20.36.15 (100408-333172415)", "usedExposureNotificationApiVersion": "2.0", "temporaryTracingKeys": [{"key": "EJWJvGkcRtuKbxQ6p1liNQ==", "intervalNumber": 2669328, "intervalCount": 98}, {"key": "EM3Q/dm9myyA9PEm7IDc5A==", "intervalNumber": 2669328, "intervalCount": 97}, {"key": "LtmuLvBnuEIY+mZ9poHa0g==", "intervalNumber": 2669328, "intervalCount": 97}, {"key": "OikIRxgL+aBW8yGp6/FUYA==", "intervalNumber": 2669328, "intervalCount": 97}, {"key": "WOG962THVaQRVpfMJOwxkQ==", "intervalNumber": 2669328, "intervalCount": 96}, {"key": "Wu64ALON2C6p0cBfa8xHwg==", "intervalNumber": 2669328, "intervalCount": 97}, {"key": "iS3aOVwVO1Id22UOoBXr2Q==", "intervalNumber": 2669328, "intervalCount": 97}, {"key": "nUNKAAq3DbzMpTeWNgq5Lg==", "intervalNumber": 2669328, "intervalCount": 97}, {"key": "qGYCL1QcJfDrfRyuFq38Sg==", "intervalNumber": 2669328, "intervalCount": 97}, {"key": "sXyTtg2gyft/eaSfnSZADg==", "intervalNumber": 2669328, "intervalCount": 97}, {"key": "1BZ8BSp34s3EXPo9tpj9IA==", "intervalNumber": 2669328, "intervalCount": 99}, {"key": "2QcGsdQWmTqsAoZGL5ys7A==", "intervalNumber": 2669328, "intervalCount": 99}, {"key": "35NYLpYIeo2dYtsOLSnbYg==", "intervalNumber": 2669328, "intervalCount": 96}, {"key": "4LFDAOt8s5g15BLQqaYk2A==", "intervalNumber": 2669328, "intervalCount": 98}, {"key": "8Bdfjbz5CI2ISeROjo5JFQ==", "intervalNumber": 2669328, "intervalCount": 98}], "results": [{"timestamp": "2020-10-02T16:30:37.849Z", "counterparts": [{"deviceName": "7018", "exposureWindows": [{"date": "2020-10-02T00:00:00Z", "reportType": 1, "scanInstances": [{"typicalAttenuationDb": 48, "minAttenuationDb": 42, "secondsSinceLastScan": 120}, {"typicalAttenuationDb": 47, "minAttenuationDb": 43, "secondsSinceLastScan": 120}, {"typicalAttenuationDb": 59, "minAttenuationDb": 52, "secondsSinceLastScan": 180}, {"typicalAttenuationDb": 71, "minAttenuationDb": 66, "secondsSinceLastScan": 300}, {"typicalAttenuationDb": 69, "minAttenuationDb": 60, "secondsSinceLastScan": 240}, {"typicalAttenuationDb": 71, "minAttenuationDb": 67, "secondsSinceLastScan": 180}], "infectiousness": 1, "calibrationConfidence": 3}]}, {"deviceName": "7019", "exposureWindows": [{"date": "2020-10-02T00:00:00Z", "reportType": 1, "scanInstances": [{"typicalAttenuationDb": 58, "minAttenuationDb": 52, "secondsSinceLastScan": 120}, {"typicalAttenuationDb": 52, "minAttenuationDb": 43, "secondsSinceLastScan": 120}, {"typicalAttenuationDb": 67, "minAttenuationDb": 55, "secondsSinceLastScan": 180}, {"typicalAttenuationDb": 67, "minAttenuationDb": 61, "secondsSinceLastScan": 300}, {"typicalAttenuationDb": 69, "minAttenuationDb": 63, "secondsSinceLastScan": 300}, {"typicalAttenuationDb": 71, "minAttenuationDb": 68, "secondsSinceLastScan": 180}], "infectiousness": 1, "calibrationConfidence": 3}]}, {"deviceName": "7016", "exposureWindows": [{"date": "2020-10-02T00:00:00Z", "reportType": 1, "scanInstances": [{"typicalAttenuationDb": 59, "minAttenuationDb": 50, "secondsSinceLastScan": 120}, {"typicalAttenuationDb": 63, "minAttenuationDb": 61, "secondsSinceLastScan": 120}, {"typicalAttenuationDb": 69, "minAttenuationDb": 65, "secondsSinceLastScan": 180}, {"typicalAttenuationDb": 74, "minAttenuationDb": 65, "secondsSinceLastScan": 300}, {"typicalAttenuationDb": 74, "minAttenuationDb": 70, "secondsSinceLastScan": 240}, {"typicalAttenuationDb": 79, "minAttenuationDb": 77, "secondsSinceLastScan": 180}], "infectiousness": 1, "calibrationConfidence": 3}]}, {"deviceName": "7004", "exposureWindows": []}, {"deviceName": "7008", "exposureWindows": [{"date": "2020-10-02T00:00:00Z", "reportType": 1, "scanInstances": [{"typicalAttenuationDb": 50, "minAttenuationDb": 45, "secondsSinceLastScan": 120}, {"typicalAttenuationDb": 65, "minAttenuationDb": 59, "secondsSinceLastScan": 120}, {"typicalAttenuationDb": 73, "minAttenuationDb": 68, "secondsSinceLastScan": 180}, {"typicalAttenuationDb": 74, "minAttenuationDb": 67, "secondsSinceLastScan": 300}, {"typicalAttenuationDb": 76, "minAttenuationDb": 68, "secondsSinceLastScan": 240}, {"typicalAttenuationDb": 85, "minAttenuationDb": 83, "secondsSinceLastScan": 180}], "infectiousness": 1, "calibrationConfidence": 3}]}, {"deviceName": "7030", "exposureWindows": [{"date": "2020-10-02T00:00:00Z", "reportType": 1, "scanInstances": [{"typicalAttenuationDb": 58, "minAttenuationDb": 54, "secondsSinceLastScan": 180}, {"typicalAttenuationDb": 57, "minAttenuationDb": 55, "secondsSinceLastScan": 300}, {"typicalAttenuationDb": 58, "minAttenuationDb": 54, "secondsSinceLastScan": 300}], "infectiousness": 1, "calibrationConfidence": 0}]}, {"deviceName": "7013", "exposureWindows": []}, {"deviceName": "7011", "exposureWindows": [{"date": "2020-10-02T00:00:00Z", "reportType": 1, "scanInstances": [{"typicalAttenuationDb": 54, "minAttenuationDb": 45, "secondsSinceLastScan": 240}], "infectiousness": 1, "calibrationConfidence": 1}, {"date": "2020-10-02T00:00:00Z", "reportType": 1, "scanInstances": [{"typicalAttenuationDb": 54, "minAttenuationDb": 51, "secondsSinceLastScan": 180}, {"typicalAttenuationDb": 56, "minAttenuationDb": 51, "secondsSinceLastScan": 300}], "infectiousness": 1, "calibrationConfidence": 1}]}]}]}, {"deviceName": "7008", "temporaryTracingKeys": [{"key": "j0EoPwRxb7iUuDXdbYl36Q==", "intervalCount": 144, "intervalNumber": 2669328}], "results": [{"counterparts": [{"deviceName": "7018", "exposureWindows": [{"date": "2020-10-02T00:00:00Z", "scanInstances": [{"typicalAttenuationDb": 40, "minAttenuationDb": 36, "secondsSinceLastScan": 180}, {"typicalAttenuationDb": 91, "minAttenuationDb": 76, "secondsSinceLastScan": 240}, {"typicalAttenuationDb": 85, "minAttenuationDb": 80, "secondsSinceLastScan": 180}, {"typicalAttenuationDb": 89, "minAttenuationDb": 83, "secondsSinceLastScan": 240}, {"typicalAttenuationDb": 92, "minAttenuationDb": 78, "secondsSinceLastScan": 180}, {"typicalAttenuationDb": 74, "minAttenuationDb": 68, "secondsSinceLastScan": 180}], "reportType": 0}]}, {"deviceName": "7019", "exposureWindows": [{"date": "2020-10-02T00:00:00Z", "scanInstances": [{"typicalAttenuationDb": 33, "minAttenuationDb": 31, "secondsSinceLastScan": 180}, {"typicalAttenuationDb": 42, "minAttenuationDb": 40, "secondsSinceLastScan": 180}, {"typicalAttenuationDb": 88, "minAttenuationDb": 82, "secondsSinceLastScan": 240}, {"typicalAttenuationDb": 78, "minAttenuationDb": 73, "secondsSinceLastScan": 180}, {"typicalAttenuationDb": 87, "minAttenuationDb": 80, "secondsSinceLastScan": 240}, {"typicalAttenuationDb": 87, "minAttenuationDb": 78, "secondsSinceLastScan": 180}], "reportType": 0}, {"date": "2020-10-02T00:00:00Z", "scanInstances": [{"typicalAttenuationDb": 79, "minAttenuationDb": 69, "secondsSinceLastScan": 180}], "reportType": 0}]}, {"deviceName": "7016", "exposureWindows": [{"date": "2020-10-02T00:00:00Z", "scanInstances": [{"typicalAttenuationDb": 35, "minAttenuationDb": 32, "secondsSinceLastScan": 180}, {"typicalAttenuationDb": 59, "minAttenuationDb": 53, "secondsSinceLastScan": 300}, {"typicalAttenuationDb": 65, "minAttenuationDb": 62, "secondsSinceLastScan": 180}, {"typicalAttenuationDb": 60, "minAttenuationDb": 57, "secondsSinceLastScan": 180}, {"typicalAttenuationDb": 59, "minAttenuationDb": 57, "secondsSinceLastScan": 240}, {"typicalAttenuationDb": 67, "minAttenuationDb": 57, "secondsSinceLastScan": 180}, {"typicalAttenuationDb": 60, "minAttenuationDb": 55, "secondsSinceLastScan": 180}], "reportType": 0}]}, {"deviceName": "7004", "exposureWindows": [{"date": "2020-10-02T00:00:00Z", "scanInstances": [{"typicalAttenuationDb": 67, "minAttenuationDb": 66, "secondsSinceLastScan": 240}, {"typicalAttenuationDb": 70, "minAttenuationDb": 68, "secondsSinceLastScan": 240}, {"typicalAttenuationDb": 69, "minAttenuationDb": 68, "secondsSinceLastScan": 180}, {"typicalAttenuationDb": 63, "minAttenuationDb": 59, "secondsSinceLastScan": 180}], "reportType": 0}, {"date": "2020-10-02T00:00:00Z", "scanInstances": [{"typicalAttenuationDb": 61, "minAttenuationDb": 61, "secondsSinceLastScan": 240}], "reportType": 0}]}, {"deviceName": "7008", "exposureWindows": []}, {"deviceName": "7030", "exposureWindows": [{"date": "2020-10-02T00:00:00Z", "scanInstances": [{"typicalAttenuationDb": 53, "minAttenuationDb": 51, "secondsSinceLastScan": 240}, {"typicalAttenuationDb": 53, "minAttenuationDb": 44, "secondsSinceLastScan": 180}, {"typicalAttenuationDb": 56, "minAttenuationDb": 51, "secondsSinceLastScan": 240}, {"typicalAttenuationDb": 52, "minAttenuationDb": 49, "secondsSinceLastScan": 180}, {"typicalAttenuationDb": 52, "minAttenuationDb": 51, "secondsSinceLastScan": 180}], "reportType": 0}]}, {"deviceName": "7013", "exposureWindows": [{"date": "2020-10-02T00:00:00Z", "scanInstances": [{"typicalAttenuationDb": 67, "minAttenuationDb": 60, "secondsSinceLastScan": 240}, {"typicalAttenuationDb": 64, "minAttenuationDb": 63, "secondsSinceLastScan": 180}, {"typicalAttenuationDb": 67, "minAttenuationDb": 62, "secondsSinceLastScan": 240}, {"typicalAttenuationDb": 73, "minAttenuationDb": 69, "secondsSinceLastScan": 180}, {"typicalAttenuationDb": 67, "minAttenuationDb": 63, "secondsSinceLastScan": 180}], "reportType": 0}]}, {"deviceName": "7011", "exposureWindows": [{"date": "2020-10-02T00:00:00Z", "scanInstances": [{"typicalAttenuationDb": 72, "minAttenuationDb": 70, "secondsSinceLastScan": 180}], "reportType": 0}, {"date": "2020-10-02T00:00:00Z", "scanInstances": [{"typicalAttenuationDb": 67, "minAttenuationDb": 65, "secondsSinceLastScan": 240}, {"typicalAttenuationDb": 70, "minAttenuationDb": 68, "secondsSinceLastScan": 180}, {"typicalAttenuationDb": 71, "minAttenuationDb": 69, "secondsSinceLastScan": 240}], "reportType": 0}]}], "timestamp": "2020-10-02T16:29:50Z"}]}, {"deviceName": "7030", "googlePlayServicesVersion": "20.33.15 (100400-330018294)", "usedExposureNotificationApiVersion": "2.0", "temporaryTracingKeys": [{"key": "BdziaslLPXRBTkq/CfCRnQ==", "intervalNumber": 2669328, "intervalCount": 98}, {"key": "FucieoYVnDTW3P5J+QVlUQ==", "intervalNumber": 2669328, "intervalCount": 99}, {"key": "SsoGL7MZ/FNysCbZ93UJbQ==", "intervalNumber": 2669328, "intervalCount": 97}, {"key": "c3pCgtVwDkOYoRPemaUabQ==", "intervalNumber": 2669328, "intervalCount": 97}, {"key": "db1+bfLgHej3rbdMEqLThQ==", "intervalNumber": 2669328, "intervalCount": 97}, {"key": "g0fyOpj/GEc70FmClk8laQ==", "intervalNumber": 2669328, "intervalCount": 97}, {"key": "mhRUcLM/gjlPk3LlR6oeXg==", "intervalNumber": 2669328, "intervalCount": 97}, {"key": "oil1agX3oq0+ngSRbarf4w==", "intervalNumber": 2669328, "intervalCount": 99}, {"key": "sJdxIslbMpMSS9MWeoCA7Q==", "intervalNumber": 2669328, "intervalCount": 98}, {"key": "2jumWPUT1QTW2HwbJ5EywA==", "intervalNumber": 2669328, "intervalCount": 97}, {"key": "6EuiXGv5UnC9drX/sbIIpA==", "intervalNumber": 2669328, "intervalCount": 99}], "results": [{"timestamp": "2020-10-02T16:20:18.248Z", "counterparts": [{"deviceName": "7018", "exposureWindows": [{"date": "2020-10-02T00:00:00Z", "reportType": 1, "scanInstances": [{"typicalAttenuationDb": 82, "minAttenuationDb": 72, "secondsSinceLastScan": 180}, {"typicalAttenuationDb": 80, "minAttenuationDb": 69, "secondsSinceLastScan": 180}], "infectiousness": 1, "calibrationConfidence": 3}]}, {"deviceName": "7019", "exposureWindows": [{"date": "2020-10-02T00:00:00Z", "reportType": 1, "scanInstances": [{"typicalAttenuationDb": 79, "minAttenuationDb": 74, "secondsSinceLastScan": 120}, {"typicalAttenuationDb": 83, "minAttenuationDb": 82, "secondsSinceLastScan": 180}, {"typicalAttenuationDb": 82, "minAttenuationDb": 73, "secondsSinceLastScan": 180}], "infectiousness": 1, "calibrationConfidence": 3}]}, {"deviceName": "7016", "exposureWindows": [{"date": "2020-10-02T00:00:00Z", "reportType": 1, "scanInstances": [{"typicalAttenuationDb": 69, "minAttenuationDb": 65, "secondsSinceLastScan": 120}, {"typicalAttenuationDb": 69, "minAttenuationDb": 65, "secondsSinceLastScan": 180}, {"typicalAttenuationDb": 70, "minAttenuationDb": 64, "secondsSinceLastScan": 180}], "infectiousness": 1, "calibrationConfidence": 3}]}, {"deviceName": "7004", "exposureWindows": []}, {"deviceName": "7008", "exposureWindows": [{"date": "2020-10-02T00:00:00Z", "reportType": 1, "scanInstances": [{"typicalAttenuationDb": 61, "minAttenuationDb": 61, "secondsSinceLastScan": 120}, {"typicalAttenuationDb": 67, "minAttenuationDb": 63, "secondsSinceLastScan": 180}, {"typicalAttenuationDb": 55, "minAttenuationDb": 49, "secondsSinceLastScan": 180}], "infectiousness": 1, "calibrationConfidence": 3}]}, {"deviceName": "7030", "exposureWindows": []}, {"deviceName": "7013", "exposureWindows": [{"date": "2020-10-02T00:00:00Z", "reportType": 1, "scanInstances": [{"typicalAttenuationDb": 61, "minAttenuationDb": 57, "secondsSinceLastScan": 120}, {"typicalAttenuationDb": 62, "minAttenuationDb": 61, "secondsSinceLastScan": 180}, {"typicalAttenuationDb": 67, "minAttenuationDb": 60, "secondsSinceLastScan": 180}], "infectiousness": 1, "calibrationConfidence": 1}]}, {"deviceName": "7011", "exposureWindows": []}]}]}, {"deviceName": "7013", "googlePlayServicesVersion": "20.33.14 (100406-327249014)", "usedExposureNotificationApiVersion": "2.0", "temporaryTracingKeys": [{"key": "Is0u1WgyHqdMAiHQak2HCA==", "intervalNumber": 2669328, "intervalCount": 144}], "results": [{"timestamp": "2020-10-02T16:29:11.917Z", "counterparts": [{"deviceName": "7018", "exposureWindows": []}, {"deviceName": "7019", "exposureWindows": []}, {"deviceName": "7016", "exposureWindows": []}, {"deviceName": "7004", "exposureWindows": []}, {"deviceName": "7008", "exposureWindows": []}, {"deviceName": "7030", "exposureWindows": []}, {"deviceName": "7013", "exposureWindows": []}, {"deviceName": "7011", "exposureWindows": []}]}]}, {"deviceName": "7011", "googlePlayServicesVersion": "20.33.15 (040306-330018294)", "usedExposureNotificationApiVersion": "2.0", "temporaryTracingKeys": [{"key": "E/WBwTTIdCV+xPmicXjoAw==", "intervalNumber": 2669328, "intervalCount": 97}, {"key": "Ir25BX4PIzYrpg7rxASQQg==", "intervalNumber": 2669328, "intervalCount": 97}, {"key": "Nbw/CiRKj1bkMTSrnJP8xg==", "intervalNumber": 2669328, "intervalCount": 97}, {"key": "OpmVYqHN6llDpsPylUaWaA==", "intervalNumber": 2669328, "intervalCount": 99}, {"key": "Q76c3wf2F57+DiGTeTSpsw==", "intervalNumber": 2669328, "intervalCount": 98}, {"key": "br1dCv9TOVQAztoj4SdSgQ==", "intervalNumber": 2669328, "intervalCount": 98}, {"key": "jC8UdYk9ltmmUQ8LNCObmA==", "intervalNumber": 2669328, "intervalCount": 99}, {"key": "wW5CJh0AozKYamjeBJHhgQ==", "intervalNumber": 2669328, "intervalCount": 99}, {"key": "9J8/B0P3MqcRNMkZQl2www==", "intervalNumber": 2669328, "intervalCount": 97}], "results": [{"timestamp": "2020-10-02T16:32:20.145Z", "counterparts": [{"deviceName": "7018", "exposureWindows": []}, {"deviceName": "7019", "exposureWindows": []}, {"deviceName": "7016", "exposureWindows": []}, {"deviceName": "7004", "exposureWindows": []}, {"deviceName": "7008", "exposureWindows": []}, {"deviceName": "7030", "exposureWindows": []}, {"deviceName": "7013", "exposureWindows": []}, {"deviceName": "7011", "exposureWindows": []}]}]}], "experimentId": "5OlZI8UFu"}